[{"messageKey":"kuali.cr.cart.message.course.code.and.section.required","message":"Course code and section required"},{"messageKey":"kuali.cr.cart.message.section.required","message":"Section required"},{"messageKey":"kuali.cr.cart.message.course.code.required","message":"Course code required"},{"messageKey":"kuali.lpr.trans.message.credit.load.exceeded","message":"Exceeded maximum credit limit"},{"messageKey":"kuali.lpr.trans.message.time.conflict","message":"Time conflict"},{"messageKey":"kuali.lpr.trans.message.waitlist.available","message":"No seats available."},{"messageKey":"kuali.lpr.trans.message.waitlist.full","message":"No seats available.<br/>(Waitlist full)"},{"messageKey":"kuali.lpr.trans.message.waitlist.not.offered","message":"No seats available.<br/>(Waitlist not offered)"},{"messageKey":"kuali.lpr.trans.message.course.not.open","message":"Registration is not currently open"},{"messageKey":"kuali.lpr.trans.message.exception","message":"There was an internal server error while processing your registration request."},{"messageKey":"kuali.lpr.trans.message.course.not.open","message":"Registration is not currently open"},{"messageKey":"kuali.lpr.trans.message.course.grade.incomplete","message":"{{courseCode}} has already been taken. Cannot repeat a course with a mark of 'I'."},{"messageKey":"kuali.lpr.trans.message.course.already.registered","message":"You are already registered for this course."},{"messageKey":"kuali.lpr.trans.item.message.exception","message":"There was an internal server error while processing this item."}]