<?xml version="1.0" encoding="UTF-8"?>
<!--

    Copyright 2010 The Kuali Foundation Licensed under the
    Educational Community License, Version 2.0 (the "License"); you may
    not use this file except in compliance with the License. You may
    obtain a copy of the License at

    http://www.osedu.org/licenses/ECL-2.0

    Unless required by applicable law or agreed to in writing,
    software distributed under the License is distributed on an "AS IS"
    BASIS, WITHOUT WARRANTIES OR CONDITIONS OF ANY KIND, either express
    or implied. See the License for the specific language governing
    permissions and limitations under the License.

-->

<beans xmlns="http://www.springframework.org/schema/beans"
       xmlns:xsi="http://www.w3.org/2001/XMLSchema-instance"
       xmlns:context="http://www.springframework.org/schema/context"
       xmlns:simple="http://cxf.apache.org/simple"
       xmlns:tx="http://www.springframework.org/schema/tx"
       xmlns:aop="http://www.springframework.org/schema/aop"
       xsi:schemaLocation="
          http://www.springframework.org/schema/context http://www.springframework.org/schema/context/spring-context-3.0.xsd
		  http://www.springframework.org/schema/beans http://www.springframework.org/schema/beans/spring-beans-3.0.xsd
		  http://cxf.apache.org/simple http://cxf.apache.org/schemas/simple.xsd
		  http://www.springframework.org/schema/tx http://www.springframework.org/schema/tx/spring-tx-3.0.xsd
		  http://www.springframework.org/schema/aop http://www.springframework.org/schema/aop/spring-aop-3.0.xsd">

    <!-- This context requires that a spring Transaction Manager named 'transactionManager' be defined -->

    <bean class="org.springframework.beans.factory.config.PropertyPlaceholderConfigurer">
		<property name="properties" value="#{bootstrapConfig.getProperties()}" />
	</bean>

	<bean id="bootstrapConfig" class="org.kuali.rice.core.impl.config.property.ConfigFactoryBean">
		<property name="configLocations">
			<list>
				<value>classpath:org/kuali/rice/standalone/config/standalone-config.xml</value>
			</list>
		</property>
	</bean>
	
	<bean class="org.springframework.beans.factory.config.MethodInvokingFactoryBean">
		<property name="staticMethod" value="org.kuali.rice.core.impl.config.property.ConfigInitializer.initialize" />
		<property name="arguments">
			<list><ref bean="bootstrapConfig"/></list>
		</property>
	</bean>

	<bean id="transactionManager" class="org.kuali.rice.krad.config.GlobalResourceLoaderServiceFactoryBean">
		<property name="serviceName" value="transactionManager" />
	</bean>

    <tx:annotation-driven transaction-manager="transactionManager"/>

    <!-- Spring to GWT servlet mapping -->
    <bean id="urlMapping"
          class="org.springframework.web.servlet.handler.SimpleUrlHandlerMapping">
        <property name="alwaysUseFullPath" value="true"/>
        <property name="urlMap">
            <map>
                <entry key="/org.kuali.student.lum.lu.ui.main.LUMMain/rpcservices/statementRpcService"
                       value-ref="statementServiceGwtController"/>
                <entry key="/org.kuali.student.lum.lu.ui.main.LUMMain/rpcservices/LuRpcService"
                        value-ref="LuRpcGwtServletController"/>
                <entry key="/org.kuali.student.lum.lu.ui.main.LUMMain/rpcservices/MessageService"
                        value-ref="messageServiceGwtController"/>
                <entry key="/org.kuali.student.lum.lu.ui.main.LUMMain/rpcservices/OrgRpcService"
                        value-ref="OrgRpcGwtServletController"/>
                <entry key="/org.kuali.student.lum.lu.ui.main.LUMMain/rpcservices/AtpRpcService"
                        value-ref="atpRpcServiceGwtController"/>
                <entry key="/org.kuali.student.lum.lu.ui.main.LUMMain/rpcservices/LoCategoryRpcService"
                        value-ref="LoCategoryRpcGwtServletController"/>
                <entry key="/org.kuali.student.lum.lu.ui.main.LUMMain/rpcservices/CreditCourseProposalRpcService"
                        value-ref="CourseProposalRpcGwtServletController"/>
                <entry key="/org.kuali.student.lum.lu.ui.main.LUMMain/rpcservices/CreditCourseRetireProposalRpcService"
                        value-ref="CourseProposalRetireRpcGwtServletController"/>
                <entry key="/org.kuali.student.lum.lu.ui.main.LUMMain/rpcservices/SecurityRpcService"
                        value-ref="SecurityRpcGwtServletController"/>
                <entry key="/org.kuali.student.lum.lu.ui.main.LUMMain/rpcservices/ServerPropertiesRpcService"
                        value-ref="ServerPropertiesServletController"/>
                <entry key="/org.kuali.student.lum.lu.ui.main.LUMMain/rpcservices/CommentRpcService"
                        value-ref="CommentRpcGwtServletController"/>
                <entry key="/org.kuali.student.lum.lu.ui.main.LUMMain/rpcservices/ProposalRpcService"
                        value-ref="ProposalRpcGwtServletController"/>
                <entry key="/org.kuali.student.lum.lu.ui.main.LUMMain/rpcservices/DocumentRpcService"
                        value-ref="DocumentRpcGwtServletController"/>
                <entry key="/org.kuali.student.lum.lu.ui.main.LUMMain/rpcservices/DocumentUpload"
                        value-ref="documentUploadGwtController"/>
                <entry key="/org.kuali.student.lum.lu.ui.main.LUMMain/rpcservices/UploadStatusRpcService"
                        value-ref="uploadStatusRpcGwtController"/>
                <entry key="/org.kuali.student.lum.lu.ui.main.LUMMain/rpcservices/SearchRpcService"
                        value-ref="searchRpcGwtController"/>
                <entry key="/org.kuali.student.lum.lu.ui.main.LUMMain/rpcservices/CourseRpcService"
                        value-ref="CourseRpcGwtServletController"/>
                <entry key="/org.kuali.student.lum.lu.ui.main.LUMMain/rpcservices/WorkflowRpcService"
                        value-ref="WorkflowRpcGwtServletController"/>
                <entry key="/org.kuali.student.lum.lu.ui.main.LUMMain/rpcservices/CluSetManagementRpcService"
                        value-ref="CluSetManagementRpcGwtServletController"/>
                <entry key="/org.kuali.student.lum.lu.ui.main.LUMMain/rpcservices/LogRpcService"
                        value-ref="LogRpcGwtServletController"/>
                <entry key="/org.kuali.student.lum.lu.ui.main.LUMMain/rpcservices/MetadataRpcService"
                       value-ref="metadataGwtController"/>
                <entry key="/org.kuali.student.lum.lu.ui.main.LUMMain/rpcservices/majorDisciplineRpcService"
                       value-ref="majorDisciplineRpcServletController"/>
                <entry key="/org.kuali.student.lum.lu.ui.main.LUMMain/rpcservices/majorDisciplineProposalRpcService"
                       value-ref="majorDisciplineProposalRpcServletController"/>
                <entry key="/org.kuali.student.lum.lu.ui.main.LUMMain/rpcservices/credentialProgramRpcService"
                       value-ref="credentialProgramRpcServletController"/>
                <entry key="/org.kuali.student.lum.lu.ui.main.LUMMain/rpcservices/coreProgramRpcService"
                       value-ref="coreProgramRpcServletController"/>
                <entry key="/org.kuali.student.lum.lu.ui.main.LUMMain/rpcservices/DependencyAnalysisRpcService"
                       value-ref="dependencyAnalysisRpcServletController"/>
				<entry key="/org.kuali.student.lum.lu.ui.main.LUMMain/rpcservices/GwtExportRpcService"
					   value-ref="GwtExportServletController" />
            </map>
        </property>
    </bean>

    <!-- Controllers -->
    <bean id="statementServiceGwtController" class="org.kuali.student.common.ws.ServletWrappingController">
        <property name="servletName" value="StatementRpcGwtServlet"/>
        <property name="servletInstance" ref="statementRpcServlet"/>
    </bean>

    <bean id="LuRpcGwtServletController"
          class="org.kuali.student.common.ws.ServletWrappingController">
        <property name="servletName" value="LuRpcGwtServlet"/>
        <property name="servletInstance" ref="LuRpcGwtServlet"/>
    </bean>

    <bean id="CourseProposalRpcGwtServletController"
          class="org.kuali.student.common.ws.ServletWrappingController">
        <property name="servletName" value="CourseProposalRpcGwtServlet"/>
        <property name="servletInstance" ref="CourseProposalRpcGwtServlet"/>
    </bean>
    
    <bean id="CourseProposalRetireRpcGwtServletController"
          class="org.kuali.student.common.ws.ServletWrappingController">
        <property name="servletName" value="CourseProposalRetireRpcGwtServlet"/>
        <property name="servletInstance" ref="CourseProposalRetireRpcGwtServlet"/>
    </bean>

    <bean id="majorDisciplineRpcServletController"
          class="org.kuali.student.common.ws.ServletWrappingController">
        <property name="servletName" value="majorDisciplineRpcServlet"/>
        <property name="servletInstance" ref="majorDisciplineRpcServlet"/>
    </bean>
    
    <bean id="majorDisciplineProposalRpcServletController"
          class="org.kuali.student.common.ws.ServletWrappingController">
        <property name="servletName" value="majorDisciplineProposalRpcServlet"/>
        <property name="servletInstance" ref="majorDisciplineProposalRpcServlet"/>
    </bean>

    <bean id="credentialProgramRpcServletController"
          class="org.kuali.student.common.ws.ServletWrappingController">
        <property name="servletName" value="CredentialProgramRpcServlet"/>
        <property name="servletInstance" ref="credentialProgramRpcServlet"/>
    </bean>

    <bean id="coreProgramRpcServletController"
          class="org.kuali.student.common.ws.ServletWrappingController">
        <property name="servletName" value="CoreProgramRpcServlet"/>
        <property name="servletInstance" ref="coreProgramRpcServlet"/>
    </bean>

    <bean id="ServerPropertiesServletController"
          class="org.kuali.student.common.ws.ServletWrappingController">
        <property name="servletName" value="ServerPropertiesServlet"/>
        <property name="servletInstance" ref="ServerPropertiesServlet"/>
    </bean>

    <bean id="messageServiceGwtController" class="org.kuali.student.common.ws.ServletWrappingController">
        <property name="servletName" value="messagesServiceGwt"/>
        <property name="servletInstance" ref="messagesServiceGwt"/>
    </bean>

    <bean id="OrgRpcGwtServletController"
          class="org.kuali.student.common.ws.ServletWrappingController">
        <property name="servletName" value="OrgRpcGwtServlet"/>
        <property name="servletInstance" ref="OrgRpcGwtServlet"/>
    </bean>

    <bean id="atpRpcServiceGwtController"
          class="org.kuali.student.common.ws.ServletWrappingController">
        <property name="servletName" value="atpRpcGwtServlet"/>
        <property name="servletInstance" ref="atpRpcGwtServlet"/>
    </bean>

    <bean id="LoCategoryRpcGwtServletController"
          class="org.kuali.student.common.ws.ServletWrappingController">
        <property name="servletName" value="LoCategoryRpcGwtServlet"/>
        <property name="servletInstance" ref="LoCategoryRpcGwtServlet"/>
    </bean>

    <bean id="SecurityRpcGwtServletController"
          class="org.kuali.student.common.ws.ServletWrappingController">
        <property name="servletName" value="SecurityGwtServlet"/>
        <property name="servletInstance" ref="SecurityGwtServlet"/>
    </bean>

    <bean id="CommentRpcGwtServletController"
          class="org.kuali.student.common.ws.ServletWrappingController">
        <property name="servletName" value="CommentRpcGwtServlet"/>
        <property name="servletInstance" ref="CommentRpcGwtServlet"/>
    </bean>

    <bean id="ProposalRpcGwtServletController"
          class="org.kuali.student.common.ws.ServletWrappingController">
        <property name="servletName" value="ProposalRpcGwtServlet"/>
        <property name="servletInstance" ref="ProposalRpcGwtServlet"/>
    </bean>

    <bean id="DocumentRpcGwtServletController"
          class="org.kuali.student.common.ws.ServletWrappingController">
        <property name="servletName" value="DocumentRpcGwtServlet"/>
        <property name="servletInstance" ref="DocumentRpcGwtServlet"/>
    </bean>

    <bean id="documentUploadGwtController" class="org.kuali.student.common.ws.ServletWrappingController">
        <property name="servletName" value="documentUpload"/>
        <property name="servletInstance" ref="documentUpload"/>
    </bean>

    <bean id="uploadStatusRpcGwtController" class="org.kuali.student.common.ws.ServletWrappingController">
        <property name="servletName" value="uploadStatusRpcGwtServlet"/>
        <property name="servletInstance" ref="uploadStatusRpcGwtServlet"/>
    </bean>

    <bean id="searchRpcGwtController" class="org.kuali.student.common.ws.ServletWrappingController">
        <property name="servletName" value="SearchDispatchRpcGwtServlet"/>
        <property name="servletInstance" ref="SearchDispatchRpcGwtServlet"/>
    </bean>

    <bean id="CourseRpcGwtServletController"
          class="org.kuali.student.common.ws.ServletWrappingController">
        <property name="servletName" value="CourseRpcGwtServlet"/>
        <property name="servletInstance" ref="CourseRpcGwtServlet"/>
    </bean>

    <bean id="WorkflowRpcGwtServletController"
          class="org.kuali.student.common.ws.ServletWrappingController">
        <property name="servletName" value="WorkflowRpcGwtServlet"/>
        <property name="servletInstance" ref="WorkflowRpcGwtServlet"/>
    </bean>

    <bean id="CluSetManagementRpcGwtServletController" class="org.kuali.student.common.ws.ServletWrappingController">
        <property name="servletName" value="CluSetManagementRpcGwtServlet"/>
        <property name="servletInstance" ref="CluSetManagementRpcGwtServlet"/>
    </bean>

    <bean id="LogRpcGwtServletController"
          class="org.kuali.student.common.ws.ServletWrappingController">
        <property name="servletName" value="LogRpcGwtServlet"/>
        <property name="servletInstance" ref="LogRpcGwtServlet"/>
    </bean>

    <bean id="metadataGwtController" class="org.kuali.student.common.ws.ServletWrappingController">
        <property name="servletName" value="MetadataRpcGwtServlet"/>
        <property name="servletInstance" ref="MetadataRpcGwtServlet"/>
    </bean>
    
    <bean id="dependencyAnalysisRpcServletController" class="org.kuali.student.common.ws.ServletWrappingController">
        <property name="servletName" value="DependencyAnalysisRpcGwtServlet"/>
        <property name="servletInstance" ref="DependencyAnalysisRpcGwtServlet"/>
    </bean>
    

    <!-- GWT Servlets -->

    <!--Course Servlet Declaration-->
    <bean id="LuRpcGwtServlet"
          class="org.kuali.student.lum.lu.ui.course.server.gwt.LuRpcGwtServlet">
        <property name="service" ref="cluClient"/>
    </bean>

    <bean id="WorkflowRpcGwtServlet"
          class="org.kuali.student.core.workflow.ui.server.gwt.WorkflowRpcGwtServlet">
        <property name="workflowDocumentActionsService" ref="workflowDocumentActionsClient"/>
        <property name="permissionService" ref="permissionServiceClient"/>
        <property name="identityService" ref="identityServiceClient"/>
        <property name="workflowDocumentService" ref="workflowDocumentClient"/>
        <property name="documentTypeService" ref="documentTypeServiceClient"/>
    </bean>

    <bean id="CourseRpcGwtServlet" class="org.kuali.student.lum.lu.ui.course.server.gwt.CourseRpcGwtServlet">
        <property name="courseService" ref="courseClient"/>
        <property name="dataService" ref="CourseDataService"/>
        <property name="statementService" ref="statementServiceClient"/>
        <property name="stateChangeService" ref="stateChangeService"/>
        <property name="cluService" ref="cluClient"/>
        <property name="proposalService" ref="proposalClient"/>
    </bean>
	
	<bean id="stateChangeService" class="org.kuali.student.lum.lu.ui.course.server.gwt.CourseStateChangeServiceImpl">
		<property name="courseService" ref="courseClient"/>
	</bean>
	
	<bean id="majorDisciplineStateChangeService" class="org.kuali.student.lum.program.server.MajorDisciplineStateChangeServiceImpl">
		<property name="programService" ref="programClient"/>
		<property name="atpService" ref="atpClient"/>
	</bean>
	<bean id="coreProgramStateChangeService" class="org.kuali.student.lum.program.server.CoreProgramStateChangeServiceImpl">
		<property name="programService" ref="programClient"/>
	</bean>
	<bean id="credentialProgramStateChangeService" class="org.kuali.student.lum.program.server.CredentialProgramStateChangeServiceImpl">
		<property name="programService" ref="programClient"/>
	</bean>
	
    <bean id="CourseProposalRpcGwtServlet"
          class="org.kuali.student.lum.lu.ui.course.server.gwt.CreditCourseProposalRpcGwtServlet">
        <property name="dataService" ref="CourseProposalDataService"/>
        <property name="copyCourseService" ref="CopyCourseService"/>
    </bean>
    
    <bean id="CourseProposalRetireRpcGwtServlet"
          class="org.kuali.student.lum.lu.ui.course.server.gwt.CreditCourseRetireProposalRpcGwtServlet">
        <property name="dataService" ref="CourseRetireProposalDataService"/>
        <property name="copyCourseService" ref="CopyCourseService"/>
    </bean>
    
    <bean id="CopyCourseService" class="org.kuali.student.lum.lu.ui.course.server.gwt.CopyCourseServiceImpl">
    	<property name="courseService" ref="courseClient"/>
	    <property name="statementService" ref="statementServiceClient"/>
	    <!-- Use the proposal data service so we can make new proposals -->
	    <property name="courseProposalDataService" ref="CourseProposalDataService"/>
	    <property name="courseDataService" ref="CourseDataService"/>
	    <property name="cluService" ref="cluClient"/>
	    <property name="proposalService" ref="proposalClient"/>
	    <property name="ignoreProperties" ref="copyCourseService.ignoreProperties" />
	</bean>
    
	<bean id="copyCourseService.ignoreProperties" class="java.util.ArrayList">
		<constructor-arg>
			<list>
				<value>transcriptTitle</value>
				<value>unitsContentOwner</value>
				<value>unitsDeployment</value>
				<value>revenues</value>
				<value>expenditure</value>
				<value>startTerm</value>
				<value>endTerm</value>
			</list>
		</constructor-arg>
	</bean>
    
    <bean id="CourseDataService"
          class="org.kuali.student.lum.lu.ui.course.server.gwt.CourseDataService">
        <property name="permissionService" ref="permissionServiceClient"/>
        <property name="courseService" ref="courseClient"/>
        <property name="cluService" ref="cluClient"/>
        <property name="transformationManager" ref="courseTransformationManager"/>
    </bean>

    <bean id="LoCategoryDataService"
          class="org.kuali.student.lum.common.server.LoCategoryDataService">
        <property name="permissionService" ref="permissionServiceClient"/>
        <property name="learningObjectiveService" ref="loClient"/>
        <property name="transformationManager" ref="loCategoryTransformationManager"/>
    </bean>

    <bean id="CourseProposalDataService"
          class="org.kuali.student.lum.lu.ui.course.server.gwt.CourseDataService">
        <property name="permissionService" ref="permissionServiceClient"/>
        <property name="courseService" ref="courseClient"/>
        <property name="proposalService" ref="proposalClient"/>
        <property name="cluService" ref="cluClient"/>
        <property name="transformationManager" ref="courseProposalTransformationManager"/>
        <property name="workflowDocumentService" ref="workflowDocumentClient"/>
    </bean>
    
    <bean id="CourseRetireProposalDataService"
          class="org.kuali.student.lum.lu.ui.course.server.gwt.CourseDataService">
        <property name="permissionService" ref="permissionServiceClient"/>
        <property name="courseService" ref="courseClient"/>
        <property name="proposalService" ref="proposalClient"/>
        <property name="cluService" ref="cluClient"/>
        <property name="transformationManager" ref="courseRetireProposalTransformationManager"/>
        <property name="workflowDocumentService" ref="workflowDocumentClient"/>
    </bean>
    
    <bean id="CluSetManagementRpcGwtServlet"
          class="org.kuali.student.lum.lu.ui.tools.server.gwt.CluSetManagementRpcGwtServlet">
        <property name="cluService" ref="cluClient"/>
        <property name="lrcService" ref="lrcClient"/>
        <property name="dataService" ref="CluSetDataService"/>
    </bean>
    
    <bean id="CluSetDataService"
          class="org.kuali.student.lum.lu.ui.tools.server.gwt.CluSetDataService">
        <property name="metadataService" ref="metadataServiceImpl"/>
        <property name="assembler" ref="CluSetManagementFilterManager"/>
    </bean>
    
    <bean id="CluSetManagementFilterManager" class="org.kuali.student.r1.common.assembly.old.AssemblerFilterManager">
        <constructor-arg ref="cluSetManagementAssembler"/>
        <property name="filters">
            <list>
                <ref bean="cluSetManagementIdTranslatorAssemblerFilter"/>
            </list>
        </property>
    </bean>

    <bean id="cluSetManagementAssembler" class="org.kuali.student.lum.lu.assembly.CluSetManagementAssembler">
        <property name="permissionService" ref="permissionServiceClient"/>
        <property name="cluService" ref="cluClient"/>
        <property name="metadataService" ref="metadataServiceImpl"/>
    </bean>
    
    <!--Program Servlet Declaration-->
    <bean id="statementRpcServlet" class="org.kuali.student.lum.program.server.StatementRpcServlet">
        <property name="statmentDataService" ref="statementDataService"/>
    </bean>
    
    <bean id="statementDataService" class="org.kuali.student.lum.program.server.StatementDataService">
        <property name="cluService" ref="cluClient"/>
        <property name="statementService" ref="statementServiceClient"/>
    </bean>
    

    <bean id="majorDisciplineProposalRpcServlet" class="org.kuali.student.lum.program.server.MajorDisciplineProposalRpcServlet">
		<property name="dataService" ref="majorDisciplineProposalDataService"/>
		<property name="programService" ref="programClient"/>
        <property name="proposalService" ref="proposalClient"/>
        <property name="statementService" ref="statementServiceClient"/>      
        <property name="stateChangeService" ref="majorDisciplineStateChangeService"/>
		<property name="cluService" ref="cluClient"/>
     </bean>

    <bean id="majorDisciplineRpcServlet" class="org.kuali.student.lum.program.server.MajorDisciplineRpcServlet">
		<property name="dataService" ref="majorDisciplineDataService"/>
		<property name="programService" ref="programClient"/>
		<property name="proposalService" ref="proposalClient"/>
        <property name="statementService" ref="statementServiceClient"/>      
        <property name="stateChangeService" ref="majorDisciplineStateChangeService"/>  
        <property name="cluService" ref="cluClient"/>
     </bean>

    <bean id="credentialProgramRpcServlet" class="org.kuali.student.lum.program.server.CredentialProgramRpcServlet">
		<property name="dataService" ref="credentialProgramDataService"/>
		<property name="programService" ref="programClient"/>
        <property name="statementService" ref="statementServiceClient"/>  
		<property name="stateChangeService" ref="credentialProgramStateChangeService"/>
		<property name="cluService" ref="cluClient"/>     
    </bean>

    <bean id="coreProgramRpcServlet" class="org.kuali.student.lum.program.server.CoreProgramRpcServlet">
		<property name="dataService" ref="coreProgramDataService"/>
		<property name="programService" ref="programClient"/>
        <property name="statementService" ref="statementServiceClient"/>       
        <property name="stateChangeService" ref="coreProgramStateChangeService"/>
        <property name="cluService" ref="cluClient"/> 
    </bean>

    <bean id="majorDisciplineDataService" class="org.kuali.student.lum.program.server.MajorDisciplineDataService">
        <property name="transformationManager" ref="majorDisciplineTransformationManager"/>
        <property name="permissionService" ref="permissionServiceClient"/>
        <property name="programService" ref="programClient"/>
    </bean>

    <bean id="majorDisciplineProposalDataService" class="org.kuali.student.lum.program.server.MajorDisciplineProposalDataService">
        <property name="transformationManager" ref="majorDisciplineProposalTransformationManager"/>
		<property name="proposalService" ref="proposalClient"/>
        <property name="permissionService" ref="permissionServiceClient"/>
        <property name="programService" ref="programClient"/>
        <property name="cluService" ref="cluClient"/>
        <property name="atpService" ref="atpClient"/>
        <property name="workflowDocumentService" ref="workflowDocumentClient"/>
    </bean>

    <bean id="credentialProgramDataService" class="org.kuali.student.lum.program.server.CredentialProgramDataService">
        <property name="transformationManager" ref="credentialProgramTransformationManager"/>
        <property name="permissionService" ref="permissionServiceClient"/>
        <property name="programService" ref="programClient"/>
        <property name="cluService" ref="cluClient"/>
    </bean>

    <bean id="coreProgramDataService" class="org.kuali.student.lum.program.server.CoreProgramDataService">
        <property name="transformationManager" ref="coreProgramTransformationManager"/>
        <property name="permissionService" ref="permissionServiceClient"/>
        <property name="programService" ref="programClient"/>
        <property name="cluService" ref="cluClient"/>
    </bean>

    <bean id="DependencyAnalysisRpcGwtServlet" class="org.kuali.student.lum.lu.ui.dependency.server.DependencyAnalysisRpcServlet">
        <property name="statementService" ref="statementServiceClient"/> 
        <property name="programService" ref="programClient"/>       
    </bean>

	<!--  Transformation Managers -->
    <bean id="courseTransformationManager" class="org.kuali.student.r1.common.assembly.transform.TransformationManager">
        <property name="metadataService" ref="metadataServiceImpl"/>
        <property name="filters">
            <list>
                <!-- <ref bean="authzFilter"/> -->
                <ref bean="idTranslatorFilter"/>
            </list>
        </property>
    </bean>

    <bean id="courseProposalTransformationManager" class="org.kuali.student.r1.common.assembly.transform.TransformationManager">
        <property name="metadataService" ref="metadataServiceImpl"/>
        <property name="filters">
            <list>
                <!-- Order of filters is important -->
                <ref bean="authzFilter"/>
                <ref bean="idTranslatorFilter"/>
                <ref bean="courseProposalWorkflowFilter"/>
                <ref bean="collaboratorFilter"/>
                <ref bean="courseInfoDtoFilter"/>
            </list>
        </property>
    </bean>
    
    <bean id="courseRetireProposalTransformationManager" class="org.kuali.student.r1.common.assembly.transform.TransformationManager">
        <property name="metadataService" ref="metadataServiceImpl"/>
        <property name="filters">
            <list>
                <!-- Order of filters is important -->
                <ref bean="authzFilter"/>
                <ref bean="idTranslatorFilter"/>
                <ref bean="courseRetireProposalWorkflowFilter"/>
                <ref bean="collaboratorFilter"/>
            </list>
        </property>
    </bean>

    <bean id="majorDisciplineTransformationManager" class="org.kuali.student.r1.common.assembly.transform.TransformationManager">
        <property name="metadataService" ref="programMetadataServiceImpl"/>
        <property name="filters">
            <list>
                <!-- Order of filters is important -->
                <ref bean="authzFilter"/>
                <ref bean="majorCredentialProgramFilter"/>
                <ref bean="versionProgramFilter"/>                
                <ref bean="idTranslatorFilter"/>
            </list>
        </property>
    </bean>

    <bean id="majorDisciplineProposalTransformationManager" class="org.kuali.student.r1.common.assembly.transform.TransformationManager">
        <property name="metadataService" ref="programMetadataServiceImpl"/>
        <property name="inboundFilters">
            <list>
                <!-- Order of filters is important -->
                <ref bean="authzFilter"/>
                <ref bean="majorCredentialProgramFilter"/>
                <ref bean="majorDisciplineProposalWorkflowFilter"/>
                <ref bean="programCollaboratorFilter"/>                
            </list>
        </property>
        <property name="outboundFilters">
            <list>
                <!-- Order of filters is important -->
                <ref bean="majorCredentialProgramFilter"/>
                <ref bean="majorDisciplineProposalWorkflowFilter"/>
                <ref bean="programCollaboratorFilter"/>                
                <ref bean="idTranslatorFilter"/>
                <ref bean="authzFilter"/>                
            </list>
        </property>
    </bean>


    <bean id="loCategoryTransformationManager" class="org.kuali.student.r1.common.assembly.transform.TransformationManager">
        <property name="metadataService" ref="metadataServiceImpl"/>
        <property name="filters">
            <list>
                <!-- Order of filters is important -->
                <ref bean="authzFilter"/>
                <ref bean="idTranslatorFilter"/>
            </list>
        </property>
    </bean>
    
    <bean id="credentialProgramTransformationManager" class="org.kuali.student.r1.common.assembly.transform.TransformationManager">
        <property name="metadataService" ref="programMetadataServiceImpl"/>
        <property name="filters">
            <list>
                <!-- Order of filters is important -->
                <ref bean="authzFilter"/>
                <ref bean="idTranslatorFilter"/>		
                <ref bean="versionCredentialProgramFilter"/>
            </list>
        </property>
    </bean>
    
    <bean id="coreProgramTransformationManager" class="org.kuali.student.r1.common.assembly.transform.TransformationManager">
        <property name="metadataService" ref="programMetadataServiceImpl"/>
        <property name="filters">
            <list>
                <!-- Order of filters is important -->
                <ref bean="authzFilter"/>
                <ref bean="coreCredentialProgramFilter"/>
                <ref bean="idTranslatorFilter"/>
                <ref bean="versionCoreProgramFilter"/>
            </list>
        </property>
    </bean>
    
    
	<!-- Transformation Manager Filters -->
    <bean id="authzFilter" class="org.kuali.student.r1.common.assembly.transform.AuthorizationFilter">
        <property name="permissionService" ref="permissionServiceClient"/>
    </bean>

    <bean id="idTranslatorFilter" class="org.kuali.student.r1.common.assembly.transform.IdTranslatorFilter">
        <constructor-arg ref="idTranslator"/>
    </bean>

	<bean id="collaboratorHelper" class = "org.kuali.student.core.rice.authorization.CollaboratorHelper">
		<property name="workflowDocumentActionsService" ref="workflowDocumentActionsClient"/>
		<property name="permissionService" ref="permissionServiceClient"/>
        <property name="identityService" ref="identityServiceClient"/>
        <property name="workflowDocumentService" ref="workflowDocumentClient"/>
        <property name="roleService" ref="roleServiceClient"/>
        <property name="documentTypeService" ref="documentTypeServiceClient"/>
	</bean>
	
	<bean id="collaboratorFilter" class = "org.kuali.student.core.assembly.transform.CollaboratorsFilter">
		<property name="metadataService" ref="metadataServiceImpl"/>
		<property name="collaboratorHelper" ref="collaboratorHelper"/>		
		<property name="proposalService" ref="proposalClient"/>
		<property name="proposalObjectType" value="org.kuali.student.core.proposal.definition.CourseProposalInfo"/>
	</bean>

	<bean id="programCollaboratorFilter" class = "org.kuali.student.core.assembly.transform.CollaboratorsFilter">
		<property name="metadataService" ref="metadataServiceImpl"/>
		<property name="collaboratorHelper" ref="collaboratorHelper"/>		
		<property name="proposalService" ref="proposalClient"/>
        <property name="proposalObjectType" value="org.kuali.student.core.proposal.definition.ProgramProposalInfo"/>	
	</bean>
	
    <bean id="parentProposalWorkflowFilter" class="org.kuali.student.core.assembly.transform.ProposalWorkflowFilter" abstract="true">
        <property name="workflowDocumentService" ref="workflowDocumentClient"/>
        <property name="workflowDocumentActionsService" ref="workflowDocumentActionsClient"/>
        <property name="proposalService" ref="proposalClient"/>
        <property name="metadataService" ref="metadataServiceImpl"/>
    </bean>

    <bean id="courseProposalWorkflowFilter" parent="parentProposalWorkflowFilter">
        <property name="proposalReferenceType" value="kuali.proposal.referenceType.clu"/>
        <property name="defaultDocType" value="kuali.proposal.type.course.create"/>
        <property name="proposalObjectType" value="org.kuali.student.core.proposal.definition.CourseProposalInfo"/>
        <property name="docTypeConfigs">
	        <list>
	        	<bean class="org.kuali.student.r1.common.assembly.transform.DocumentTypeConfiguration">
	        		<property name="documentType" value="kuali.proposal.type.course.create"/>
	        		<property name="defaultDocumentTitle" value="{courseTitle}"/>
	        		<property name="docContentFieldMap">
	           			<map>
		                	<entry key="cluId" value="id"/>
		                	<entry key="orgId" value="unitsContentOwner/0"/>
	           			</map>
					</property>
	            </bean>
	            <bean class="org.kuali.student.r1.common.assembly.transform.DocumentTypeConfiguration">
	        		<property name="documentType" value="kuali.proposal.type.course.create.admin"/>
	        		<property name="defaultDocumentTitle" value="{courseTitle}"/>
	        		<property name="docContentFieldMap">
	           			<map>
		                	<entry key="cluId" value="id"/>
		                	<entry key="orgId" value="unitsContentOwner/0"/>
	           			</map>
					</property>
	            </bean>
	        	<bean class="org.kuali.student.r1.common.assembly.transform.DocumentTypeConfiguration">
	        		<property name="documentType" value="kuali.proposal.type.course.modify"/>
					<property name="defaultDocumentTitle" value="Modify: {courseTitle}"/>	            	
					<property name="docContentFieldMap">					
	           			<map>
		                	<entry key="cluId" value="id"/>
		                	<entry key="orgId" value="unitsContentOwner/0"/>
	           			</map>
	           		</property>
				</bean>
				<bean class="org.kuali.student.r1.common.assembly.transform.DocumentTypeConfiguration">
	        		<property name="documentType" value="kuali.proposal.type.course.modify.admin"/>
					<property name="defaultDocumentTitle" value="Modify: {courseTitle}"/>	            	
					<property name="docContentFieldMap">					
	           			<map>
		                	<entry key="cluId" value="id"/>
		                	<entry key="orgId" value="unitsContentOwner/0"/>
	           			</map>
	           		</property>
				</bean>
				<bean class="org.kuali.student.r1.common.assembly.transform.DocumentTypeConfiguration">
	        		<property name="documentType" value="kuali.proposal.type.course.retire"/>
	        		<property name="defaultDocumentTitle" value="Retire: {courseTitle}"/>
	        		<property name="docContentFieldMap">
	           			<map>
		                	<entry key="cluId" value="id"/>
		                	<entry key="orgId" value="unitsContentOwner/0"/>
	           			</map>
					</property>
	            </bean>            
 			</list>
		</property>			
    </bean>
    
    <bean id="courseRetireProposalWorkflowFilter" parent="parentProposalWorkflowFilter">
        <property name="proposalReferenceType" value="kuali.proposal.referenceType.clu"/>
        <property name="defaultDocType" value="kuali.proposal.type.course.retire"/>
        <property name="proposalObjectType" value="org.kuali.student.core.proposal.definition.RetireCourseProposalInfo"/>
        <property name="idTranslator" ref="idTranslator"/>
        <property name="docTypeConfigs">
	        <list>
				<bean class="org.kuali.student.r1.common.assembly.transform.DocumentTypeConfiguration">
	        		<property name="documentType" value="kuali.proposal.type.course.retire"/>
	        		<property name="defaultDocumentTitle" value="Retire: {courseTitle}"/>
	        		<property name="docContentFieldMap">
	           			<map>
		                	<entry key="cluId" value="id"/>
		                	<entry key="orgId" value="unitsContentOwner/0"/>
	           			</map>
					</property>
	            </bean>         
 			</list>
		</property>			
    </bean>

    <bean id="majorDisciplineProposalWorkflowFilter" parent="parentProposalWorkflowFilter">
        <property name="proposalReferenceType" value="kuali.proposal.referenceType.clu"/>
        <property name="defaultDocType" value="kuali.proposal.type.majorDiscipline.modify"/>
        <property name="proposalObjectType" value="org.kuali.student.core.proposal.definition.ProgramProposalInfo"/>
        <property name="docTypeConfigs">
	        <list>
	        	<bean class="org.kuali.student.r1.common.assembly.transform.DocumentTypeConfiguration">
	        		<property name="documentType" value="kuali.proposal.type.majorDiscipline.modify"/>
	        		<property name="defaultDocumentTitle" value="{shortTitle}"/>
	        		<property name="docContentFieldMap">
	           			<map>
		                	<entry key="cluId" value="id"/>
		                	<entry key="orgId" value="unitsContentOwner/0"/>
	           			</map>
					</property>
	            </bean>
			</list>
		</property>			
    </bean>

    <bean id="majorCredentialProgramFilter" class="org.kuali.student.lum.program.server.transform.MajorCredentialProgramFilter">
        <property name="metadataService" ref="metadataServiceImpl"/>
        <property name="programService" ref="programClient"/>
    </bean>

    <bean id="coreCredentialProgramFilter" class="org.kuali.student.lum.program.server.transform.CoreCredentialProgramFilter">
        <property name="cluService" ref="cluClient"/>
    </bean>

    <bean id="versionProgramFilter" class="org.kuali.student.lum.program.server.transform.VersionProgramFilter">
        <property name="programService" ref="programClient"/>
        <property name="metadataService" ref="metadataServiceImpl"/>
        <property name="proposalObjectType" value="org.kuali.student.core.proposal.definition.ProgramProposalInfo"/>
        <property name="atpService" ref="atpClient"/>
    </bean>

    <bean id="versionCoreProgramFilter" class="org.kuali.student.lum.program.server.transform.VersionCoreProgramFilter">
        <property name="programService" ref="programClient"/>
        <property name="metadataService" ref="metadataServiceImpl"/>
        <property name="proposalObjectType" value="org.kuali.student.core.proposal.definition.ProgramProposalInfo"/>
    </bean>

    <bean id="versionCredentialProgramFilter" class="org.kuali.student.lum.program.server.transform.VersionCredentialProgramFilter">
        <property name="programService" ref="programClient"/>
        <property name="metadataService" ref="metadataServiceImpl"/>
        <property name="proposalObjectType" value="org.kuali.student.core.proposal.definition.ProgramProposalInfo"/>
    </bean>

    <bean id="courseInfoDtoFilter" class = "org.kuali.student.lum.lu.assembly.CourseInfoDtoFilter"/>

    <bean id="metadataServiceImpl" class="org.kuali.student.r1.common.assembly.dictionary.MetadataServiceImpl">
        <property name="dictionaryServices">
            <list>
                <ref bean="courseClient"/>
                <ref bean="proposalClient"/>
            </list>
        </property>
        <property name="uiLookupContext" value="${ks.lum.ui.lookupContextLocations}"/>
    </bean>

    <bean id="programMetadataServiceImpl" class="org.kuali.student.lum.program.server.metadata.ProgramMetadataServiceImpl">
        <property name="dictionaryServices">
            <list>
                <ref bean="programClient"/>
            </list>
        </property>
        <property name="uiLookupContext" value="${ks.lum.ui.lookupContextLocations}"/>
    </bean>

    <bean id="idTranslator" class="org.kuali.student.r1.common.assembly.util.IdTranslator">
        <constructor-arg ref="searchDispatcher"/>
    </bean>

    <bean id="cluSetManagementIdTranslatorAssemblerFilter" class="org.kuali.student.lum.lu.assembly.CluSetManagementIdTranslatorAssemblerFilter">
        <constructor-arg ref="idTranslator"/>
        <property name="metadataService" ref="metadataServiceImpl"/>
    </bean>

    <bean id="idTranslatorAssemblerFilter" class="org.kuali.student.r1.common.assembly.old.IdTranslatorAssemblerFilter">
        <constructor-arg ref="idTranslator"/>
    </bean>

    <bean id="ServerPropertiesServlet"
          class="org.kuali.student.common.ui.server.gwt.ServerPropertiesRpcGwtServlet">
    </bean>

    <bean id="messagesServiceGwt"
          class="org.kuali.student.common.ui.server.gwt.MessagesRpcGwtServlet">
        <property name="serviceImpl" ref="messageClient" />
    </bean>

    <bean id="CommentRpcGwtServlet"
          class="org.kuali.student.core.comments.ui.server.CommentRpcGwtServlet">
        <property name="service" ref="commentClient"/>
        <property name="identityService" ref="identityServiceClient"/>
        <property name="permissionService" ref="permissionServiceClient"/>
    </bean>

    <bean id="ProposalRpcGwtServlet"
          class="org.kuali.student.core.proposal.ui.server.gwt.ProposalRpcGwtServlet">
        <property name="service" ref="proposalClient"/>
    </bean>

    <bean id="DocumentRpcGwtServlet"
          class="org.kuali.student.core.document.ui.server.DocumentRpcGwtServlet">
        <property name="service" ref="documentService"/>
        <property name="permissionService" ref="permissionServiceClient"/>
    </bean>

    <bean id="OrgRpcGwtServlet"
          class="org.kuali.student.core.organization.ui.server.gwt.OrgRpcGwtServlet">
        <property name="service" ref="orgClient"/>
        <property name="identityService" ref="identityServiceClient"/>
        <property name="identityServiceNonCached" ref="identityServiceClientNonCached"/>
    </bean>

    <bean id="atpRpcGwtServlet"
          class="org.kuali.student.core.atp.ui.server.AtpRpcGwtServlet">
        <property name="service" ref="atpClient"/>
    </bean>

    <bean id="LoCategoryRpcGwtServlet"
          class="org.kuali.student.lum.lu.ui.course.server.gwt.LoCategoryRpcGwtServlet">
        <property name="loService" ref="loClient"/>
        <property name="dataService" ref="LoCategoryDataService"/>
    </bean>

    <bean id="SecurityGwtServlet"
          class="org.kuali.student.common.ui.server.gwt.SecurityRpcGwtServlet">
          <property name="permissionService" ref="permissionServiceClient"/>
    </bean>

    <bean id="documentUpload" class="org.kuali.student.core.document.ui.server.upload.UploadServlet">
        <property name="documentService" ref="documentService"/>
    </bean>

    <bean id="uploadStatusRpcGwtServlet" class="org.kuali.student.core.document.ui.server.UploadStatusRpcGwtServlet">
    </bean>

    <bean id="SearchDispatchRpcGwtServlet" class="org.kuali.student.common.ui.server.gwt.SearchDispatchRpcGwtServlet">
        <property name="searchDispatcher" ref="searchDispatcher"/>
        <property name="idTranslatorFilter" ref="idTranslatorFilter"/>
        <property name="cachingEnabled" value="true"/>
    </bean>
    <bean id="searchDispatcher" class="org.kuali.student.r2.common.class1.search.SearchServiceDispatcherImpl">
        <property name="searchServices">
            <list>
                <ref bean="cluClient"/>
                <ref bean="loClient"/>
                <ref bean="orgClient"/>
                <ref bean="atpClient"/>
                <ref bean="personSearchClient"/>
                <ref bean="proposalClient"/>
                <ref bean="enumServiceClient"/>
                <ref bean="lrcClient"/>
                <ref bean="subjectCodeClient"/>
                <ref bean="typeSearchService"/>
            </list>
        </property>
    </bean>

    <bean id="LogRpcGwtServlet" class="org.kuali.student.common.ui.server.gwt.LogRpcGwtServlet"/>

    <bean id="MetadataRpcGwtServlet" class="org.kuali.student.common.ui.server.gwt.MetadataRpcGwtServlet">
         <property name="serviceImpl" ref="metadataServiceImpl"/>        
    </bean>

    <!-- Service clients -->
    <bean id="courseClient" class="org.kuali.rice.ksb.messaging.KSBClientProxyFactoryBean">
        <property name="serviceEndpointInterface" value="org.kuali.student.r2.lum.course.service.CourseService"/>
        <property name="serviceQName" value="{http://student.kuali.org/wsdl/course}CourseService"/>
    </bean>

    <bean id="programClient" class="org.kuali.rice.ksb.messaging.KSBClientProxyFactoryBean">
        <property name="serviceEndpointInterface" value="org.kuali.student.r2.lum.program.service.ProgramService"/>
        <property name="serviceQName" value="{http://student.kuali.org/wsdl/program}ProgramService"/>
    </bean>

    <bean id="cluClient" class="org.kuali.rice.ksb.messaging.KSBClientProxyFactoryBean">
        <property name="serviceEndpointInterface" value="org.kuali.student.r2.lum.clu.service.CluService"/>
        <property name="serviceQName" value="{http://student.kuali.org/wsdl/clu}CluService"/>
    </bean>

    <bean id="commentClient" class="org.kuali.rice.ksb.messaging.KSBClientProxyFactoryBean">
        <property name="serviceEndpointInterface" value="org.kuali.student.r1.core.comment.service.CommentService"/>
        <property name="serviceQName" value="{http://student.kuali.org/wsdl/comment}CommentService"/>
    </bean>

    <bean id="statementServiceClient" class="org.kuali.rice.ksb.messaging.KSBClientProxyFactoryBean">
        <property name="serviceEndpointInterface" value="org.kuali.student.r1.core.statement.service.StatementService"/>
        <property name="serviceQName" value="{http://student.kuali.org/wsdl/statement}StatementService"/>
    </bean>

    <bean id="orgClient" class="org.kuali.rice.ksb.messaging.KSBClientProxyFactoryBean">
        <property name="serviceEndpointInterface"
                  value="org.kuali.student.r2.core.organization.service.OrganizationService"/>
        <property name="serviceQName" value="{http://student.kuali.org/wsdl/organization}OrganizationService"/>
    </bean>

    <bean id="atpClient" class="org.kuali.rice.ksb.messaging.KSBClientProxyFactoryBean">
        <property name="serviceEndpointInterface" value="org.kuali.student.r2.core.atp.service.AtpService"/>
        <property name="serviceQName" value="{http://student.kuali.org/wsdl/atp}AtpService"/>
    </bean>

    <bean id="personSearchClient" class="org.kuali.rice.ksb.messaging.KSBClientProxyFactoryBean">
        <property name="serviceEndpointInterface" value="org.kuali.student.r2.core.search.service.SearchService"/>
        <property name="serviceQName" value="{http://student.kuali.org/wsdl/personsearch}PersonSearchService"/>
    </bean>

    <bean id="messageClient" class="org.kuali.rice.ksb.messaging.KSBClientProxyFactoryBean">
        <property name="serviceEndpointInterface" value="org.kuali.student.r2.common.messages.service.MessageService"/>
        <property name="serviceQName" value="{http://student.kuali.org/wsdl/message}MessageService"/>
    </bean>

    <bean id="subjectCodeClient" class="org.kuali.rice.ksb.messaging.KSBClientProxyFactoryBean">
        <property name="serviceEndpointInterface" value="org.kuali.student.r1.core.subjectcode.service.SubjectCodeService"/>
        <property name="serviceQName" value="{http://student.kuali.org/wsdl/subjectCode}SubjectCodeService"/>
    </bean>

    <bean id="proposalClient" class="org.kuali.rice.ksb.messaging.KSBClientProxyFactoryBean">
        <property name="serviceEndpointInterface" value="org.kuali.student.r1.core.proposal.service.ProposalService"/>
        <property name="serviceQName" value="{http://student.kuali.org/wsdl/proposal}ProposalService"/>
    </bean>

    <bean id="loClient" class="org.kuali.rice.ksb.messaging.KSBClientProxyFactoryBean">
        <property name="serviceEndpointInterface" value="org.kuali.student.r2.lum.lo.service.LearningObjectiveService"/>
        <property name="serviceQName" value="{http://student.kuali.org/wsdl/lo}LearningObjectiveService"/>
    </bean>

    <bean id="lrcClient" class="org.kuali.rice.ksb.messaging.KSBClientProxyFactoryBean">
        <property name="serviceEndpointInterface" value="org.kuali.student.r2.lum.lrc.service.LRCService"/>
        <property name="serviceQName" value="{http://student.kuali.org/wsdl/lrc}LearningResultService"/>
    </bean>

    <!-- TODO: RICE-R2.0 UPGRADE - change the qName when R2.0 deploys this service -->
    <bean id="workflowDocumentClient" class="org.kuali.rice.ksb.messaging.KSBClientProxyFactoryBean">
        <property name="serviceEndpointInterface" value="org.kuali.rice.kew.api.document.WorkflowDocumentService"/>
        <property name="serviceQName" value="{http://rice.kuali.org/kew/v2_0}workflowDocumentService"/>
    </bean>

    <bean id="workflowDocumentActionsClient" class="org.kuali.rice.ksb.messaging.KSBClientProxyFactoryBean">
        <property name="serviceEndpointInterface"
                  value="org.kuali.rice.kew.api.action.WorkflowDocumentActionsService"/>
        <property name="serviceQName" value="{http://rice.kuali.org/kew/v2_0}workflowDocumentActionsService"/>
    </bean>

    <bean id="documentService" class="org.kuali.rice.ksb.messaging.KSBClientProxyFactoryBean">
        <property name="serviceEndpointInterface" value="org.kuali.student.r2.core.document.service.DocumentService"/>
        <property name="serviceQName" value="{http://student.kuali.org/wsdl/document}DocumentService"/>
    </bean>

    <bean id="searchService" class="org.kuali.rice.ksb.messaging.KSBClientProxyFactoryBean">
        <property name="serviceEndpointInterface" value="org.kuali.student.r2.core.search.service.SearchService"/>
        <property name="serviceQName" value="{http://student.kuali.org/wsdl/search}SearchService"/>
    </bean>

    <!-- TODO: RICE-R2.0 UPGRADE - caching disabled in M7 will be revisited prior to 2.0 release -->
    <bean id="permissionServiceClient" class="org.kuali.rice.ksb.messaging.KSBClientProxyFactoryBean">
        <property name="serviceEndpointInterface" value="org.kuali.rice.kim.api.permission.PermissionService"/>
        <property name="serviceQName" value="{http://rice.kuali.org/kim/v2_0}permissionService"/>
    </bean>

    <bean id="identityServiceClient" class="org.kuali.rice.ksb.messaging.KSBClientProxyFactoryBean">
        <property name="serviceEndpointInterface" value="org.kuali.rice.kim.api.identity.IdentityService"/>
        <property name="serviceQName" value="{http://rice.kuali.org/kim/v2_0}identityService"/>
    </bean>
    
    <bean id="identityServiceClientNonCached" class="org.kuali.rice.ksb.messaging.KSBClientProxyFactoryBean">
        <property name="serviceEndpointInterface" value="org.kuali.rice.kim.api.identity.IdentityService" />
        <property name="serviceQName" value="{http://rice.kuali.org/kim/v2_0}identityService" />
    </bean>

    <bean id="enumServiceClient" class="org.kuali.rice.ksb.messaging.KSBClientProxyFactoryBean">
        <property name="serviceEndpointInterface"
                  value="org.kuali.student.r2.core.enumerationmanagement.service.EnumerationManagementService"/>
        <property name="serviceQName"
                  value="{http://student.kuali.org/wsdl/enumerationmanagement}EnumerationManagementService"/>
    </bean>

    <bean id="roleServiceClient" class="org.kuali.rice.ksb.messaging.KSBClientProxyFactoryBean">
        <property name="serviceEndpointInterface" value="org.kuali.rice.kim.api.role.RoleService"/>
        <property name="serviceQName" value="{http://rice.kuali.org/kim/v2_0}roleService"/>
    </bean>

    <bean id="documentTypeServiceClient" class="org.kuali.rice.ksb.messaging.KSBClientProxyFactoryBean">
        <property name="serviceEndpointInterface" value="org.kuali.rice.kew.api.doctype.DocumentTypeService"/>
        <property name="serviceQName" value="{http://rice.kuali.org/kew/v2_0}documentTypeService"/>
    </bean>

    <bean id="typeClient" class="org.kuali.rice.ksb.messaging.KSBClientProxyFactoryBean">
        <property name="serviceEndpointInterface" value="org.kuali.student.r2.core.class1.type.service.TypeService"/>
        <property name="serviceQName" value="{http://student.kuali.org/wsdl/type}TypeService"/>
    </bean>

    <bean id="typeSearchService" class="org.kuali.student.r2.lum.service.search.TypeSearchServiceImpl">
        <property name="typeSearches">
            <list>
                <!--  Configure type searches. -->
                <bean class="org.kuali.student.r2.lum.service.search.ResultComponentTypeSearch">
                    <property name="typeService" ref="typeClient"/>
                </bean>
                <bean class="org.kuali.student.r2.lum.service.search.AtpSeasonTypeSearch">
                    <property name="typeService" ref="typeClient"/>
                </bean>
                <bean class="org.kuali.student.r2.lum.service.search.AtpDurationTypeSearch">
                    <property name="typeService" ref="typeClient"/>
                </bean>
            </list>
        </property>
    </bean>

    <!-- Export services and service to present exported file to user in browser -->
	<bean id="GwtExportServletController"
		class="org.kuali.student.common.ws.ServletWrappingController">
		<property name="servletName" value="GwtExportRpcService" />
		<property name="servletInstance" ref="GwtExportRpcService" />
	</bean>

	<bean id="GwtExportRpcService"
		class="org.kuali.student.common.ui.server.gwt.ExportGwtRpcServlet">
		<property name="reportProcessor" ref="ReportProcessor"/>
	</bean>
	
	<!-- Screen Report Processor -->
	<bean id="ReportProcessor"
          class="org.kuali.student.common.ui.server.screenreport.jasper.JasperScreenReportProcessorImpl">
    </bean>
    
   	<!-- metadata caching config -->
   	<bean id="ksLumGwtCacheManager" class="net.sf.ehcache.CacheManager">
		<constructor-arg index="0" type="java.net.URL" value="${ks.lum.gwt.cache.config.file}" />
	</bean>

	<bean id="metadataMethodCacheAdvisor" class="org.kuali.student.r1.common.assembly.util.spring.MetadataMethodEhcacheAdvice">
		<property name="cacheName" value="metadataCache" />
		<property name="cacheManager" ref="ksLumGwtCacheManager"/>
		<property name="enabled" value="${ks.lum.gwt.metadata.enable.caching}"/>
	</bean>
	
	<aop:config>
		<aop:aspect id="metadataCacheAroundSearch" ref="metadataMethodCacheAdvisor">
			<aop:around pointcut="execution(*  org.kuali.student.r1.common.assembly.dictionary.MetadataServiceImpl.getMetadata(..))" method="getFromCache" />
			<aop:around pointcut="execution(*  org.kuali.student.r1.common.assembly.dictionary.MetadataServiceImpl.getMetadataByWorkflowNode(..))" method="getFromCache" />
			<aop:around pointcut="execution(*  org.kuali.student.lum.program.server.metadata.ProgramMetadataServiceImpl.getMetadata(..))" method="getFromCache" />
			<aop:around pointcut="execution(*  org.kuali.student.lum.program.server.metadata.ProgramMetadataServiceImpl.getMetadataByWorkflowNode(..))" method="getFromCache" />
		</aop:aspect>
	</aop:config>
    
</beans>